panel_lca_app_concept/__init__.py
panel_lca_app_concept/bw.py
panel_lca_app_concept/charts.py
panel_lca_app_concept/data.py
panel_lca_app_concept/demo_databases.py
panel_lca_app_concept/helpers.py
panel_lca_app_concept/test_location.py
panel_lca_app_concept/theming.py
panel_lca_app_concept/components/__init__.py
panel_lca_app_concept/components/menu.py
panel_lca_app_concept/pages/__init__.py
panel_lca_app_concept/pages/calculation_setup.py
panel_lca_app_concept/pages/home.py
panel_lca_app_concept/pages/impact_overview.py
panel_lca_app_concept-0.1.4.dist-info/METADATA
panel_lca_app_concept-0.1.4.dist-info/WHEEL
panel_lca_app_concept-0.1.4.dist-info/entry_points.txt
panel_lca_app_concept-0.1.4.dist-info/top_level.txt
panel_lca_app_concept-0.1.4.dist-info/RECORD
