Metadata-Version: 2.4
Name: panel_lca_app_concept
Version: 0.1.4
Summary: Panel app for an PMI LCA tool concept
Author-email: Timo Diepers <timo.diepers@ltt.rwth-aachen.de>
Maintainer-email: Timo Diepers <timo.diepers@ltt.rwth-aachen.de>
Project-URL: source, https://github.com/TimoDiepers/panel-lca-app-concept
Project-URL: homepage, https://github.com/TimoDiepers/panel-lca-app-concept
Project-URL: tracker, https://github.com/TimoDiepers/panel-lca-app-concept/issues
Classifier: Development Status :: 4 - Beta
Classifier: Programming Language :: Python
Classifier: Programming Language :: Python :: 3
Classifier: Programming Language :: Python :: 3.9
Classifier: Programming Language :: Python :: 3.10
Classifier: Programming Language :: Python :: 3.11
Classifier: Programming Language :: Python :: 3.12
Classifier: Natural Language :: English
Classifier: Operating System :: OS Independent
Classifier: Topic :: Scientific/Engineering
Requires-Python: >=3.9
Requires-Dist: bw2data==4.5
Requires-Dist: bw2calc==2.1
Requires-Dist: bw2io==0.9.11
Requires-Dist: panel
Requires-Dist: panel-material-ui
Requires-Dist: plotly
Provides-Extra: testing
Requires-Dist: panel-lca-app-concept; extra == "testing"
Requires-Dist: pytest; extra == "testing"
Requires-Dist: pytest-cov; extra == "testing"
Requires-Dist: python-coveralls; extra == "testing"
Provides-Extra: dev
Requires-Dist: build; extra == "dev"
Requires-Dist: pre-commit; extra == "dev"
Requires-Dist: pylint; extra == "dev"
Requires-Dist: pytest; extra == "dev"
Requires-Dist: pytest-cov; extra == "dev"
Requires-Dist: pytest-randomly; extra == "dev"
Requires-Dist: setuptools; extra == "dev"
